rpeasings/__init__.py
rpeasings/__init__.pyi
rpeasings/_rpeasings.cpython-314-aarch64-linux-musl.so
rpeasings/py.typed
rpeasings/include/docstrings.h
rpeasings/include/rpeasings.h
rpeasings-0.4.6.dist-info/METADATA
rpeasings-0.4.6.dist-info/WHEEL
rpeasings-0.4.6.dist-info/top_level.txt
rpeasings-0.4.6.dist-info/RECORD
rpeasings-0.4.6.dist-info/licenses/LICENSE
