Metadata-Version: 2.4
Name: rpeasings
Version: 0.4.6
Summary: Robert Penner's easings functions in python
Author-email: Michael Lamertz <michael.lamertz@gmail.com>
Project-URL: homepage, https://github.com/dickerdackel/rpeasings
Project-URL: bugtracker, https://github.com/DickerDackel/rpeasings/issues
Classifier: Development Status :: 3 - Alpha
Classifier: Intended Audience :: Developers
Classifier: Topic :: Games/Entertainment
Classifier: Topic :: Software Development :: Libraries :: pygame
License-File: LICENSE
Dynamic: license-file
